{
    "version": "24.12.0-0",
    "homepage": "https://github.com/hoppscotch/releases",
    "description": "Hoppscotch Desktop App releases.",
    "license": "MIT License",
    "url": "https://github.com/hoppscotch/releases/releases/download/v24.12.0-0/Hoppscotch_win_x64.msi",
    "hash": "3ea4973366bd99de0de2f723f8d13221ea28062c6e19d6fd83bf88e2a993c9c4",
    "extract_dir": "PFiles\\Hoppscotch",
    "checkver": {
        "url": "https://github.com/hoppscotch/releases/releases/latest",
        "regex": "/releases/tag/(?:v|V)?([\\d.-]+)"
    },
    "autoupdate": {
        "url": "https://github.com/hoppscotch/releases/releases/download/v$version/Hoppscotch_win_x64.msi"
    },
    "shortcuts": [
        [
            "Hoppscotch.exe",
            "Hoppscotch"
        ]
    ]
}
