{
    "version": "15.0.13",
    "homepage": "https://www.navicat.com.cn",
    "architecture": {
        "64bit": {
            "url": "http://download.navicat.com.cn/download/navicat150_premium_cs_x64.exe",
            "hash": "9474a7d7efc2d7c8df4336e13418bcaf2cd8124a5a75be65fe883f4266e24dd7"
        },
        "32bit": {
            "url": "http://download.navicat.com.cn/download/navicat150_premium_cs_x86.exe",
            "hash": "baf0476d6bf2ca4f398ede75612de62624dfca222fe28ffbe2382c51f5efd258"
        }
    },
    "checkver": {
        "url": "http://navicat.com.cn/products/navicat-premium-release-note",
        "re": "Navicat Premium \\(Windows\\) version ([\\d\\.]+)"
    },
    "autoupdate": {
        "architecture": {
            "64bit": {
                "url": "http://download.navicat.com.cn/download/navicat$majorVersion$minorVersion_premium_cs_x64.exe"
            },
            "32bit": {
                "url": "http://download.navicat.com.cn/download/navicat$majorVersion$minorVersion_premium_cs_x86.exe"
            }
        }
    },
    "innosetup": true,
    "shortcuts": [
        [
            "navicat.exe",
            "Navicat Premium"
        ]
    ]
}
