{
    "version": "15.0.13",
    "homepage": "https://www.navicat.com",
    "architecture": {
        "64bit": {
            "url": "http://download.navicat.com/download/navicat150_premium_en_x64.exe",
            "hash": "21483d2567ab1bd0efa6fe263d8b40918e90aff5792a4f4e9529a7e93a1b080f"
        },
        "32bit": {
            "url": "http://download.navicat.com/download/navicat150_premium_en_x86.exe",
            "hash": "01e10abb9cba35de7229bb4c5e7ed6b6844efa4ae52351d48045c03ee00c5dc3"
        }
    },
    "checkver": {
        "url": "https://www.navicat.com/en/products/navicat-premium-release-note",
        "re": "Navicat Premium \\(Windows\\) version ([\\d\\.]+)"
    },
    "autoupdate": {
        "architecture": {
            "64bit": {
                "url": "http://download.navicat.com/download/navicat$majorVersion$minorVersion_premium_en_x64.exe"
            },
            "32bit": {
                "url": "http://download.navicat.com/download/navicat$majorVersion$minorVersion_premium_en_x86.exe"
            }
        }
    },
    "innosetup": true,
    "shortcuts": [
        [
            "navicat.exe",
            "Navicat Premium"
        ]
    ]
}
