{
    "version": "1-05-2204180",
    "homepage": "https://developers.weixin.qq.com/miniprogram/dev/devtools/devtools.html",
    "architecture": {
        "64bit": {
            "url": "https://servicewechat.com/wxa-dev-logic/download_redirect?type=x64&from=mpwiki&download_version=1052204180&version_type=1#/dl.7z",
            "hash": "119bb9217a349bf79f7cf01ee181c442681d6e2d4d286325fca6d7948558fd72"
        },
        "32bit": {
            "url": "https://servicewechat.com/wxa-dev-logic/download_redirect?type=ia32&from=mpwiki&download_version=1052204180&version_type=1#/dl.7z",
            "hash": "e88e6a9b9077e436655330dd08b8654935efdb6d10f0a11d1248499ae789be49"
        }
    },
    "checkver": {
        "url": "https://developers.weixin.qq.com/miniprogram/dev/devtools/stable.html",
        "re": "_([\\d-]+)-Windows-64-"
    },
    "autoupdate": {
        "architecture": {
            "64bit": {
                "url": "https://servicewechat.com/wxa-dev-logic/download_redirect?type=x64&from=mpwiki&download_version=$cleanVersion&version_type=1#/dl.7z"
            },
            "32bit": {
                "url": "https://servicewechat.com/wxa-dev-logic/download_redirect?type=ia32&from=mpwiki&download_version=$cleanVersion&version_type=1#/dl.7z"
            }
        }
    },
    "shortcuts": [
        [
            "微信开发者工具.exe",
            "微信开发者工具"
        ]
    ]
}
